wifilab/__init__.py
wifilab/__main__.py
wifilab/app.py
wifilab-1.2.0.dist-info/licenses/LICENSE
wifilab-1.2.0.dist-info/METADATA
wifilab-1.2.0.dist-info/WHEEL
wifilab-1.2.0.dist-info/entry_points.txt
wifilab-1.2.0.dist-info/top_level.txt
wifilab-1.2.0.dist-info/RECORD
