Metadata-Version: 2.4
Name: wifilab
Version: 1.2.0
Summary: Wi-Fi Lab Controller: Safe WiFi testing toolkit with scanning, fake AP, DNS redirection.
Home-page: https://github.com/ZahidServers/WiFi-Lab-Controller
Author: Mohammed Zahid Wadiwale
Author-email: info@webaon.com
License: BSD-3-Clause
Classifier: Programming Language :: Python :: 3
Classifier: License :: OSI Approved :: BSD License
Classifier: Operating System :: POSIX :: Linux
Classifier: Topic :: Security
Classifier: Topic :: System :: Networking
Requires-Python: >=3.9
License-File: LICENSE
Dynamic: author
Dynamic: author-email
Dynamic: classifier
Dynamic: description
Dynamic: description-content-type
Dynamic: home-page
Dynamic: license
Dynamic: license-file
Dynamic: requires-python
Dynamic: summary
